oarepo_model_builder_ccmm/__init__.py
oarepo_model_builder_ccmm/builtin_models/__init__.py
oarepo_model_builder_ccmm/builtin_models/ccmm.yaml
oarepo_model_builder_ccmm-0.2.1.dist-info/licenses/LICENSE
oarepo_model_builder_ccmm-0.2.1.dist-info/METADATA
oarepo_model_builder_ccmm-0.2.1.dist-info/WHEEL
oarepo_model_builder_ccmm-0.2.1.dist-info/entry_points.txt
oarepo_model_builder_ccmm-0.2.1.dist-info/top_level.txt
oarepo_model_builder_ccmm-0.2.1.dist-info/RECORD
