Metadata-Version: 2.4
Name: oarepo-model-builder-ccmm
Version: 0.2.1
License-File: LICENSE
Requires-Dist: oarepo-model-builder-tests>=4.0.0
Requires-Dist: oarepo-model-builder>=4.0.0
Requires-Dist: oarepo-model-builder-files>=4.0.0
Requires-Dist: oarepo-model-builder-drafts>=1.0.4
Requires-Dist: oarepo-model-builder-drafts-files>=4.0.0
Requires-Dist: oarepo-model-builder-workflows>=1.0.0
Requires-Dist: oarepo-model-builder-rdm>=1.0.0
Requires-Dist: oarepo-model-builder-multilingual>=1.0.0
Requires-Dist: oarepo-model-builder-ui>=1.0.0
Requires-Dist: oarepo-model-builder-vocabularies
Dynamic: license-file
